tomosphero/__init__.py
tomosphero/geometry.py
tomosphero/loss.py
tomosphero/model.py
tomosphero/plotting.py
tomosphero/raytracer.py
tomosphero/retrieval.py
tomosphero/test_all.py
tomosphero/test_examples.py
tomosphero/test_model.py
tomosphero/test_plotting.py
tomosphero/test_raytracer.py
tomosphero/test_retrieval.py
tomosphero-0.0.2.dist-info/licenses/LICENSE
tomosphero-0.0.2.dist-info/METADATA
tomosphero-0.0.2.dist-info/WHEEL
tomosphero-0.0.2.dist-info/top_level.txt
tomosphero-0.0.2.dist-info/RECORD
