Metadata-Version: 2.4
Name: tomosphero
Version: 0.0.2
Summary: PyTorch volume raytracer in spherical coordinates
Author-email: Evan Widloski <evan_gh@widloski.com>
License-File: LICENSE
Requires-Dist: torch>=1.12.1
Requires-Dist: tqdm
Dynamic: license-file
